datapeach_wrapper/__init__.py
datapeach_wrapper/wrapper.py
datapeach_wrapper-1.0.6.dist-info/METADATA
datapeach_wrapper-1.0.6.dist-info/WHEEL
datapeach_wrapper-1.0.6.dist-info/top_level.txt
datapeach_wrapper-1.0.6.dist-info/RECORD
