Metadata-Version: 2.1
Name: datapeach-wrapper
Version: 1.0.6
Summary: datapeach wrapper
Home-page: UNKNOWN
Author: datapeach
Author-email: datapeach@gigarion.com
License: MIT
Platform: UNKNOWN
Requires-Python: >=3.8
Requires-Dist: nbconvert
Requires-Dist: nbformat
Requires-Dist: pandas
Requires-Dist: pulsar-client
Requires-Dist: pyyaml
Requires-Dist: requests
